{
  "templateType": "performance",
  "url": "https://finance.yahoo.co.jp/quote/${stockCode}/performance?styl=performance",
  "_note": "This config extracts structured financial performance data from Yahoo Finance Japan. The 'structuredPerformanceData' field contains parsed financial metrics in object format for easier processing. Use with Japanese stock codes like 143A.T, 7203.T, etc.",
  "selectors": {
    "stockInfo": {
      "selector": "h1, .symbol",
      "transform": "cleanStockSymbol"
    },
    "period":{
      "selector": "tbody > tr > th",
      "multiple": false,
      "transform": "extractFreeCashflow"
    },
    "revenue":{
      "selector": "tbody > tr > td:nth-child(1) > span",
      "multiple": false,
      "transform": "extractFreeCashflow"
    },
    "grossProfitMargin": {
      "selector": "tbody > tr > td:nth-child(2) > span",
      "multiple": false,
      "transform": "extractOperatingCashflow"
    },
    "operationProfit": {
      "selector": "tbody > tr > td:nth-child(3) > span",
      "multiple": false,
      "transform": "extractInvestingCashflow"
    },
    "operationProfitMargin": {
      "selector": "tbody > tr > td:nth-child(4) > span",
      "multiple": false,
      "transform": "extractFinancingCashflow"
    },
    "ordinaryProfit": {
      "selector": "tbody > tr > td:nth-child(5) > span",
      "multiple": false,
      "transform": "extractFinancingCashflow"
    },
    "ordinaryProfitMargin": {
      "selector": "tbody > tr > td:nth-child(6) > span",
      "multiple": false,
      "transform": "extractFinancingCashflow"
    },
    "netProfit": {
      "selector": "tbody > tr > td:nth-child(7) > span",
      "multiple": false,
      "transform": "extractFinancingCashflow"
    },
    "accountingMethod": {
      "selector": "tbody > tr > td:nth-child(8) > span",
      "multiple": false,
      "transform": "extractFinancingCashflow"
    },
    "financialDataUpdateDate": {
      "selector": "tbody > tr > td:nth-child(9) > span",
      "multiple": false,
      "transform": "extractFinancingCashflow"
    },
    "data": {
      "selector"": "body",
      "transform"": "extractTableData",
    }
  },
  "headers": {
    "Accept": "text/html,application/xhtml+xml,application/xml;q=0.9,image/webp,image/apng,*/*;q=0.8",
    "Accept-Language": "ja,en-US;q=0.9,en;q=0.8",
    "Accept-Encoding": "gzip, deflate, br",
    "Cache-Control": "no-cache",
    "User-Agent": "Mozilla/5.0 (Macintosh; Intel Mac OS X 10_15_7) AppleWebKit/537.36 (KHTML, like Gecko) Chrome/120.0.0.0 Safari/537.36"
  },
  "options": {
    "timeout": 30000,
    "retries": 3,
    "headless": true,
    "screenshot": false,
    "encoding": "utf-8",
    "domainDelay": 5000,
    "waitFor": 5000,
    "viewport": {
      "width": 1920,
      "height": 1080
    }
  },
  "variables": {
    "stockCode": "7901.T",
    "baseUrl": "https://finance.yahoo.co.jp"
  },
  "export": {
    "formats": ["json", "csv"],
    "filename": "yahoo_finance_jp_performance_${stockCode}"
  }
}
